zope.generations-6.0-py3.12-nspkg.pth
zope/generations/README.rst
zope/generations/__init__.py
zope/generations/configure.zcml
zope/generations/generations.py
zope/generations/interfaces.py
zope/generations/subscriber.zcml
zope/generations/utility.py
zope/generations/demo/__init__.py
zope/generations/demo/evolve1.py
zope/generations/demo/evolve2.py
zope/generations/demo/evolve3.py
zope/generations/demo/install.py
zope/generations/demo2/__init__.py
zope/generations/demo3/__init__.py
zope/generations/demo3/install.py
zope/generations/tests/__init__.py
zope/generations/tests/test_backwardcompat.py
zope/generations/tests/test_generations.py
zope/generations/tests/test_zcml.py
zope_generations-6.0.dist-info/licenses/LICENSE.txt
zope_generations-6.0.dist-info/METADATA
zope_generations-6.0.dist-info/WHEEL
zope_generations-6.0.dist-info/namespace_packages.txt
zope_generations-6.0.dist-info/top_level.txt
zope_generations-6.0.dist-info/RECORD
